README.md
setup.py
fum/__init__.py
fum/__main__.py
fum/fum.py
fum.egg-info/PKG-INFO
fum.egg-info/SOURCES.txt
fum.egg-info/dependency_links.txt
fum.egg-info/entry_points.txt
fum.egg-info/top_level.txt