Metadata-Version: 2.1
Name: fum
Version: 1
Summary: something not meant to be
Home-page: UNKNOWN
Author: madhavth
Author-email: 
License: UNKNOWN
Platform: UNKNOWN
